[{		
	"series" :"first_steps",
	"language" : "por",
	"description":"Primeiros passos é um recurso que tem como objetivo ajudar você a entender o que significa ser um seguidor de Cristo e a crescer neste entendimento. Estas lições nos ajudarão a descobrir e colocar em prática alguns dos princípios básicos do que significa seguir a Cristo e falar Dele com outras pessoas.",
	"chapters": [
		{"id": 1, 
			"title": "Introdução", 
			"description": "Conectando pessoas a Jesus e uns aos outros",
			"count":"1",
			"filename":"step1" 
		},
		{"id": 2, 
			"title": "Segurança", 
			"description":"Como uma pessoa que recebeu Jesus pode saber com certeza que vai passar a eternidade com Deus?" ,
			"count":"2",
			"filename":"step2" 
		},
		{"id": 3,
			"title": "Experimentando o amor e o perdão de Deus",
			"description": "Como podemos experimentar constantemente um relacionamento íntimo com Deus?",
			"count":"3",
			"filename":"step3" 
		},
			{"id": 4, 
			"title": "Compartilhando Jesus com outros", 
			"description": "Se ter um relacionamento com Jesus é uma notícia tão boa, como podemos falar para outros sobre essa boa notícia?",
			"count":"4",
			"filename":"step4" 
		},
		{"id": 5, 
			"title": "Crescendo espiritualmente",
			"description": "Como podemos continuar a crescer em nosso relacionamento com Jesus?",
			"count":"5",
			"filename":"step5" 
		},
		{"id": 6, 
			"title": "Quem é o Espírito Santo?", 
			"description": "Quem nos ajuda a entender e a experimentar as coisas sobre as quais temos falado nessas últimas semanas?",
			"count":"6",
			"filename":"step6" 
		},
		{"id": 7, 
			"title": "Vivendo pelo poder de Deus", 
			"description": "“Como vivemos a vida cristã quando ela parece ser tão difícil de ser vivida?”" ,
			"count":"7",
			"filename":"step7" 
		},
		{"id": 8, 
			"title": "Satisfeito?", 
			"description": "" ,
			"count":"",
			"filename":"satisfied" 
		},
		{"id": 9, 
			"title": "Qual é o próximo", 
			"description": "" ,
			"count":"",
			"filename":"next" 
		},
		{"id": 998, 
			"title": "Sobre", 
			"description": "" ,
			"count":"",
			"filename":"intro" 
		},
		{"id": 999, 
			"title": "dicas", 
			"description": "" ,
			"count":"",
			"filename":"tips" 
		}

	]
}]
