[
  {
    "id": 1,
    "name": "life",
    "title": "Life Issues",
    "folder": "|ContentFolder|/myfriends",
    "index": "life",
    "style": "|CountryCODE|/myfriends.css",
    "image": "issues.jpg",
    "format": "series",
    "instructions": ""
  },
  {
    "id": 2,
    "name": "basics",
    "title": "Basic Conversations",
    "folder": "|ContentFolder|/myfriends",
    "index": "basics",
    "style": "|CountryCODE|/myfriends.css",
    "image": "basics.jpg",
    "format": "series",
    "instructions": ""
  },
  {
    "id": 3,
    "name": "community",
    "title": "Live Community",
    "folder": "|ContentFolder|/myfriends",
    "page": "community",
    "style": "|CountryCODE|/myfriends.css",
    "image": "community.jpg",
    "format": "page"
  },
  {
    "id": 4,
    "name": "firststeps",
    "title": "First Steps",
    "folder": "|ContentFolder|/first_steps",
    "index": "first_steps",
    "style": "|CountryCODE|/fsteps.css",
    "image": "firststeps.jpg",
    "format": "series",
    "instructions": ""
  },
  {
    "id": 5,
    "name": "compass",
    "title": "Compass",
    "folder": "|ContentFolder|/compass",
    "index": "compass-chapters",
    "style": "|CountryCODE|/compass.css",
    "image": "compass.jpg",
    "format": "series",
    "instructions": ""
  },
  {
    "id": 6,
    "name": "about",
    "title": "About MyFriends",
    "folder": "|ContentFolder|/myfriends",
    "page": "community",
    "style": "|CountryCODE|/myfriends.css",
    "image": "about.jpg",
    "format": "page"
  }
]
